BookerWikiTool/OPENAI_TOKEN.txt
BookerWikiTool/__init__.py
BookerWikiTool/__main__.py
BookerWikiTool/bili.py
BookerWikiTool/chatgpt.py
BookerWikiTool/codelint.py
BookerWikiTool/comp_epub.py
BookerWikiTool/crawl_wx.py
BookerWikiTool/epub_tool.py
BookerWikiTool/fetch_links.py
BookerWikiTool/flatten.py
BookerWikiTool/fmt.py
BookerWikiTool/keyframe.py
BookerWikiTool/md_tool.py
BookerWikiTool/mdalign.py
BookerWikiTool/medium.py
BookerWikiTool/pdf_tool.py
BookerWikiTool/pdg_tool.py
BookerWikiTool/ppt2pdf.py
BookerWikiTool/toggle_bw.py
BookerWikiTool/tomd.js
BookerWikiTool/util.py
BookerWikiTool/webarchive.py
BookerWikiTool/wx_external.py
BookerWikiTool/zip_tool.py
BookerWikiTool/assets/7z.dll
BookerWikiTool/assets/7z.exe
BookerWikiTool/assets/Pdg2Pic.exe
BookerWikiTool/assets/Pdg2Pic.htm
BookerWikiTool/assets/Pdg2Pic.ini
BookerWikiTool/assets/PwdDic.txt
BookerWikiTool/assets/__init__.py
BookerWikiTool/assets/jbig2.exe
BookerWikiTool/assets/jbig2enc.dll
BookerWikiTool/assets/unrar.exe
BookerWikiTool-2023.5.24.0.dist-info/LICENSE
BookerWikiTool-2023.5.24.0.dist-info/METADATA
BookerWikiTool-2023.5.24.0.dist-info/WHEEL
BookerWikiTool-2023.5.24.0.dist-info/entry_points.txt
BookerWikiTool-2023.5.24.0.dist-info/top_level.txt
BookerWikiTool-2023.5.24.0.dist-info/RECORD
